metamart_source_redshift/__init__.py
metamart_source_redshift/adapters.py
metamart_source_redshift/base.py
metamart_source_redshift/loader.py
metamart_source_redshift/models.py
metamart_source_redshift/package_definitions.py
metamart_source_redshift-0.1.1.dist-info/METADATA
metamart_source_redshift-0.1.1.dist-info/WHEEL
metamart_source_redshift-0.1.1.dist-info/RECORD
