Metadata-Version: 2.1
Name: metamart_source_redshift
Version: 0.1.1
Summary: 
Home-page: https://www.metamart.io/
License: Elastic-2.0
Author: Ian Eaves
Author-email: ian@metamart.io
Requires-Python: >=3.9,<4.0
Classifier: License :: Other/Proprietary License
Classifier: Programming Language :: Python :: 3
Classifier: Programming Language :: Python :: 3.9
Classifier: Programming Language :: Python :: 3.10
Classifier: Programming Language :: Python :: 3.11
Classifier: Programming Language :: Python :: 3.12
Requires-Dist: metamart-schemas (>=0.2.7-alpha1,<0.3.0)
Requires-Dist: multimethod (>=1.8,<2.0,!=1.11)
Requires-Dist: pydantic[dotenv] (>=1.10.7,<2.0.0)
Requires-Dist: redshift-connector (>=2.0.911,<3.0.0)
Project-URL: Documentation, https://docs.metamart.io/
Project-URL: Repository, https://github.com/meta-mart/metamart-core/tree/master/metamart-integrations/source-redshift
